{
    "code": 1,
    "msg": "ok",
    "data": {
        "lx": {
            "1": "充值",
            "2": "消费",
            "3": "交易",
            "4": "转帐",
            "5": "提成",
            "6": "提现",
            "7": "退款",
            "8": "结算",
            "9": "代充",
            "99": "其他"
        },
        "zt": [
            "正常",
            "退款"
        ],
        "fs": {
            "1": "入款",
            "2": "扣款"
        },
        "zu": {
            "1": "域名注册",
            "2": "续费域名",
            "3": "转入域名",
            "4": "发送PUSH",
            "5": "接收PUSH",
            "6": "出售域名",
            "7": "购买域名",
            "10": "入库域名",
            "13": "开通代理",
            "16": "购买优惠券",
            "20": "支付宝充值",
            "21": "Paypal充值",
            "29": "电汇充值",
            "30": "服务商充值",
            "99": "其他"
        },
        "qian": {
            "qian": "0.00",
            "xfqian": "0.00",
            "zqian": "0.00",
            "dqian": "0.00",
            "czqian": "0.00"
        }
    }
}